nonebot_plugin_emojilike_automonkey/__init__.py
nonebot_plugin_emojilike_automonkey/config.py
nonebot_plugin_emojilike_automonkey/face.py
nonebot_plugin_emojilike_automonkey-0.1.1.dist-info/LICENSE
nonebot_plugin_emojilike_automonkey-0.1.1.dist-info/METADATA
nonebot_plugin_emojilike_automonkey-0.1.1.dist-info/WHEEL
nonebot_plugin_emojilike_automonkey-0.1.1.dist-info/RECORD
