Metadata-Version: 2.3
Name: nonebot-plugin-emojilike-automonkey
Version: 0.1.1
Summary: nonebot2贴猴插件
Keywords: nonebot,nonebot2,emoji,like
Author: BG4JEC
Author-email: BG4JEC@hotmail.com
Requires-Python: >=3.10,<4.0
Classifier: Programming Language :: Python :: 3
Classifier: Programming Language :: Python :: 3.10
Classifier: Programming Language :: Python :: 3.11
Classifier: Programming Language :: Python :: 3.12
Classifier: Programming Language :: Python :: 3.13
Requires-Dist: emoji (>=2.0.0,<3.0.0)
Requires-Dist: nonebot-adapter-onebot (>=2.4.6,<3.0.0)
Requires-Dist: nonebot-plugin-apscheduler (>=0.5.0,<1)
Requires-Dist: nonebot2 (>=2.4.0,<3.0.0)
Requires-Dist: nonebot_plugin_localstore (>=0.7.3,<1)
Project-URL: Repository, https://github.com/2580m/nonebot-plugin-emojilike-automonkey
